{"cameraMode":{"drawMode":0,"name":"Shaded","section":"Shading Mode"},"sceneLighting":true,"audioPlay":false,"sceneViewState":{"showFog":true,"showMaterialUpdate":false,"showSkybox":true,"showFlares":true,"showImageEffects":true,"showParticleSystems":true},"in2DMode":false,"pivot":{"x":0.8341132402420044,"y":0.8173567056655884,"z":4.325424671173096},"rotation":{"x":0.11815821379423142,"y":-0.5801947712898254,"z":0.08557143807411194,"w":0.8013322353363037},"size":1.6449227333068848,"orthographic":false}